superior_scoring_rules/__init__.py
superior_scoring_rules/superior_scoring_rules.py
superior_scoring_rules-1.0.6.dist-info/METADATA
superior_scoring_rules-1.0.6.dist-info/WHEEL
superior_scoring_rules-1.0.6.dist-info/top_level.txt
superior_scoring_rules-1.0.6.dist-info/RECORD
