Metadata-Version: 2.1
Name: superior-scoring-rules
Version: 1.0.6
Summary: PBS and PLL are superior evaluation metrics for probabilistic classifiers, fixing flaws in Brier Score (MSE) and Log Loss (Cross-Entropy). Strictly proper, consistent, and better for model selection, early stopping, and checkpointing.
Home-page: https://github.com/Ruhallah93/superior-scoring-rules
Author: Rouhollah Ahmadian
Author-email: ruhallah.ahmadian@gmail.com
Classifier: Programming Language :: Python :: 3
Classifier: License :: OSI Approved :: BSD License
Classifier: Operating System :: OS Independent
Requires-Python: >=3.0.0
Requires-Dist: tensorflow>=2.0.0
